{
    "documents": [
        {
            "id": "id__2082",
            "sentiment": "negative",
            "confidenceScores": {
                "positive": 0,
                "neutral": 0.04,
                "negative": 0.95
            },
            "sentences": [
                {
                    "sentiment": "negative",
                    "confidenceScores": {
                        "positive": 0,
                        "neutral": 0.01,
                        "negative": 0.99
                    },
                    "offset": 0,
                    "length": 86,
                    "text": "I had high hopes for these running shoes, but they failed to live up to expectations. ",
                    "targets": [
                        {
                            "sentiment": "negative",
                            "confidenceScores": {
                                "positive": 0,
                                "negative": 1
                            },
                            "offset": 35,
                            "length": 5,
                            "text": "shoes",
                            "relations": [
                                {
                                    "relationType": "assessment",
                                    "ref": "#/documents/0/sentences/0/assessments/0"
                                }
                            ]
                        }
                    ],
                    "assessments": [
                        {
                            "sentiment": "negative",
                            "confidenceScores": {
                                "positive": 0,
                                "negative": 1
                            },
                            "offset": 51,
                            "length": 6,
                            "text": "failed",
                            "isNegated": false
                        }
                    ]
                },
                {
                    "sentiment": "negative",
                    "confidenceScores": {
                        "positive": 0,
                        "neutral": 0.01,
                        "negative": 0.99
                    },
                    "offset": 86,
                    "length": 88,
                    "text": "The fit is awkward and uncomfortable, causing blisters and soreness even on short runs. ",
                    "targets": [
                        {
                            "sentiment": "negative",
                            "confidenceScores": {
                                "positive": 0,
                                "negative": 1
                            },
                            "offset": 90,
                            "length": 3,
                            "text": "fit",
                            "relations": [
                                {
                                    "relationType": "assessment",
                                    "ref": "#/documents/0/sentences/1/assessments/0"
                                },
                                {
                                    "relationType": "assessment",
                                    "ref": "#/documents/0/sentences/1/assessments/1"
                                },
                                {
                                    "relationType": "assessment",
                                    "ref": "#/documents/0/sentences/1/assessments/2"
                                }
                            ]
                        }
                    ],
                    "assessments": [
                        {
                            "sentiment": "negative",
                            "confidenceScores": {
                                "positive": 0,
                                "negative": 1
                            },
                            "offset": 97,
                            "length": 7,
                            "text": "awkward",
                            "isNegated": false
                        },
                        {
                            "sentiment": "negative",
                            "confidenceScores": {
                                "positive": 0,
                                "negative": 1
                            },
                            "offset": 109,
                            "length": 13,
                            "text": "uncomfortable",
                            "isNegated": false
                        },
                        {
                            "sentiment": "negative",
                            "confidenceScores": {
                                "positive": 0,
                                "negative": 1
                            },
                            "offset": 132,
                            "length": 8,
                            "text": "blisters",
                            "isNegated": false
                        }
                    ]
                },
                {
                    "sentiment": "negative",
                    "confidenceScores": {
                        "positive": 0,
                        "neutral": 0.01,
                        "negative": 0.99
                    },
                    "offset": 174,
                    "length": 97,
                    "text": "The cushioning is insufficient, leaving my feet feeling battered and bruised after each workout. ",
                    "targets": [
                        {
                            "sentiment": "negative",
                            "confidenceScores": {
                                "positive": 0.02,
                                "negative": 0.98
                            },
                            "offset": 178,
                            "length": 10,
                            "text": "cushioning",
                            "relations": [
                                {
                                    "relationType": "assessment",
                                    "ref": "#/documents/0/sentences/2/assessments/0"
                                }
                            ]
                        },
                        {
                            "sentiment": "negative",
                            "confidenceScores": {
                                "positive": 0.02,
                                "negative": 0.98
                            },
                            "offset": 217,
                            "length": 4,
                            "text": "feet",
                            "relations": [
                                {
                                    "relationType": "assessment",
                                    "ref": "#/documents/0/sentences/2/assessments/1"
                                },
                                {
                                    "relationType": "assessment",
                                    "ref": "#/documents/0/sentences/2/assessments/2"
                                }
                            ]
                        }
                    ],
                    "assessments": [
                        {
                            "sentiment": "negative",
                            "confidenceScores": {
                                "positive": 0.02,
                                "negative": 0.98
                            },
                            "offset": 192,
                            "length": 12,
                            "text": "insufficient",
                            "isNegated": false
                        },
                        {
                            "sentiment": "negative",
                            "confidenceScores": {
                                "positive": 0.01,
                                "negative": 0.99
                            },
                            "offset": 230,
                            "length": 8,
                            "text": "battered",
                            "isNegated": false
                        },
                        {
                            "sentiment": "negative",
                            "confidenceScores": {
                                "positive": 0.02,
                                "negative": 0.98
                            },
                            "offset": 243,
                            "length": 7,
                            "text": "bruised",
                            "isNegated": false
                        }
                    ]
                },
                {
                    "sentiment": "negative",
                    "confidenceScores": {
                        "positive": 0,
                        "neutral": 0.01,
                        "negative": 0.99
                    },
                    "offset": 271,
                    "length": 72,
                    "text": "The design is uninspired, and the build quality feels cheap and flimsy. ",
                    "targets": [
                        {
                            "sentiment": "negative",
                            "confidenceScores": {
                                "positive": 0.04,
                                "negative": 0.96
                            },
                            "offset": 275,
                            "length": 6,
                            "text": "design",
                            "relations": [
                                {
                                    "relationType": "assessment",
                                    "ref": "#/documents/0/sentences/3/assessments/0"
                                }
                            ]
                        },
                        {
                            "sentiment": "negative",
                            "confidenceScores": {
                                "positive": 0.02,
                                "negative": 0.98
                            },
                            "offset": 305,
                            "length": 13,
                            "text": "build quality",
                            "relations": [
                                {
                                    "relationType": "assessment",
                                    "ref": "#/documents/0/sentences/3/assessments/1"
                                },
                                {
                                    "relationType": "assessment",
                                    "ref": "#/documents/0/sentences/3/assessments/2"
                                }
                            ]
                        }
                    ],
                    "assessments": [
                        {
                            "sentiment": "negative",
                            "confidenceScores": {
                                "positive": 0.04,
                                "negative": 0.96
                            },
                            "offset": 285,
                            "length": 10,
                            "text": "uninspired",
                            "isNegated": false
                        },
                        {
                            "sentiment": "negative",
                            "confidenceScores": {
                                "positive": 0.02,
                                "negative": 0.98
                            },
                            "offset": 325,
                            "length": 5,
                            "text": "cheap",
                            "isNegated": false
                        },
                        {
                            "sentiment": "negative",
                            "confidenceScores": {
                                "positive": 0.03,
                                "negative": 0.97
                            },
                            "offset": 335,
                            "length": 6,
                            "text": "flimsy",
                            "isNegated": false
                        }
                    ]
                },
                {
                    "sentiment": "negative",
                    "confidenceScores": {
                        "positive": 0.01,
                        "neutral": 0.22,
                        "negative": 0.77
                    },
                    "offset": 343,
                    "length": 77,
                    "text": "After just a few weeks of use, the soles started to peel away from the shoe. ",
                    "targets": [
                        {
                            "sentiment": "negative",
                            "confidenceScores": {
                                "positive": 0.01,
                                "negative": 0.99
                            },
                            "offset": 378,
                            "length": 5,
                            "text": "soles",
                            "relations": [
                                {
                                    "relationType": "assessment",
                                    "ref": "#/documents/0/sentences/4/assessments/0"
                                },
                                {
                                    "relationType": "assessment",
                                    "ref": "#/documents/0/sentences/4/assessments/1"
                                }
                            ]
                        }
                    ],
                    "assessments": [
                        {
                            "sentiment": "negative",
                            "confidenceScores": {
                                "positive": 0.01,
                                "negative": 0.99
                            },
                            "offset": 395,
                            "length": 4,
                            "text": "peel",
                            "isNegated": false
                        },
                        {
                            "sentiment": "negative",
                            "confidenceScores": {
                                "positive": 0.01,
                                "negative": 0.99
                            },
                            "offset": 395,
                            "length": 9,
                            "text": "peel away",
                            "isNegated": false
                        }
                    ]
                },
                {
                    "sentiment": "negative",
                    "confidenceScores": {
                        "positive": 0,
                        "neutral": 0.01,
                        "negative": 0.99
                    },
                    "offset": 420,
                    "length": 83,
                    "text": "Overall, I would not recommend these running shoes to anyone serious about fitness.",
                    "targets": [
                        {
                            "sentiment": "negative",
                            "confidenceScores": {
                                "positive": 0,
                                "negative": 1
                            },
                            "offset": 457,
                            "length": 13,
                            "text": "running shoes",
                            "relations": [
                                {
                                    "relationType": "assessment",
                                    "ref": "#/documents/0/sentences/5/assessments/0"
                                }
                            ]
                        }
                    ],
                    "assessments": [
                        {
                            "sentiment": "negative",
                            "confidenceScores": {
                                "positive": 0,
                                "negative": 1
                            },
                            "offset": 441,
                            "length": 9,
                            "text": "recommend",
                            "isNegated": true
                        }
                    ]
                }
            ],
            "warnings": []
        }
    ],
    "errors": [],
    "modelVersion": "2022-11-01"
}